MANIFEST.in
README.rst
setup.py
django_multiple_email_backends/__init__.py
django_multiple_email_backends/backend.py
django_multiple_email_backends/models.py
django_multiple_email_backends.egg-info/PKG-INFO
django_multiple_email_backends.egg-info/SOURCES.txt
django_multiple_email_backends.egg-info/dependency_links.txt
django_multiple_email_backends.egg-info/not-zip-safe
django_multiple_email_backends.egg-info/requires.txt
django_multiple_email_backends.egg-info/top_level.txt