Metadata-Version: 1.0
Name: django-multiple-email-backends
Version: 0.1a4
Summary: Want to send through more than one interface? E.g. SMTP and database? This is your solution
Home-page: https://github.com/KristianOellegaard/django-multiple-email-backends
Author: Kristian Ollegaard
Author-email: kristian@oellegaard.com
License: BSD
Keywords: django email backend multiple
Platform: UNKNOWN
Classifier: Topic :: Utilities
